blk_utils/__init__.py
blk_utils/utils.py
blk_utils-0.1.3.dist-info/METADATA
blk_utils-0.1.3.dist-info/WHEEL
blk_utils-0.1.3.dist-info/top_level.txt
blk_utils-0.1.3.dist-info/RECORD
