Metadata-Version: 2.1
Name: blk-utils
Version: 0.1.3
Summary: Small Utility Library
Home-page: https://blk-utils.readthedocs.io/
Author: Brian Christopher
Author-email: bcr@blackarbs.com
License: MIT
Classifier: Intended Audience :: Developers
Classifier: License :: OSI Approved :: MIT License
Classifier: Programming Language :: Python
Classifier: Programming Language :: Python :: 3.6
Classifier: Programming Language :: Python :: 3.7
Classifier: Programming Language :: Python :: 3.8
Classifier: Programming Language :: Python :: 3.9
Classifier: Programming Language :: Python :: 3.10
Classifier: Programming Language :: Python :: 3.11
Classifier: Programming Language :: Python :: 3.12
Classifier: Operating System :: OS Independent
Requires-Dist: pandas
Requires-Dist: hypothesis
Requires-Dist: timeutils
